MANIFEST.in
README.rst
setup.cfg
setup.py
ckanext/__init__.py
ckanext/redmine/__init__.py
ckanext/redmine/celery_import.py
ckanext/redmine/plugin.py
ckanext/redmine/tasks.py
ckanext_redmine_autoissues.egg-info/PKG-INFO
ckanext_redmine_autoissues.egg-info/SOURCES.txt
ckanext_redmine_autoissues.egg-info/dependency_links.txt
ckanext_redmine_autoissues.egg-info/entry_points.txt
ckanext_redmine_autoissues.egg-info/requires.txt
ckanext_redmine_autoissues.egg-info/top_level.txt