Metadata-Version: 1.1
Name: ckanext-redmine-autoissues
Version: 1.0.0
Summary: Allows creating tickets in redmine instance
Home-page: https://github.com/sorki/ckanext-redmine-autoissues
Author: sorki
Author-email: srk@48.io
License: AGPL
Keywords: CKAN redmine synchronization
Platform: UNKNOWN
Classifier: Development Status :: 4 - Beta
Classifier: License :: OSI Approved :: GNU Affero General Public License v3 or later (AGPLv3+)
Classifier: Programming Language :: Python :: 2.6
Classifier: Programming Language :: Python :: 2.7
